LICENSE.txt
README.rst
setup.py
quantumdiceware/__init__.py
quantumdiceware/__main__.py
quantumdiceware/__quantumdiceware.py
quantumdiceware/diceware_word_list.txt
quantumdiceware/quantumdiceware.py
quantumdiceware.egg-info/PKG-INFO
quantumdiceware.egg-info/SOURCES.txt
quantumdiceware.egg-info/dependency_links.txt
quantumdiceware.egg-info/entry_points.txt
quantumdiceware.egg-info/requires.txt
quantumdiceware.egg-info/top_level.txt