Metadata-Version: 2.1
Name: quantumdiceware
Version: 4.1
Summary: Generates Diceware passphrases from quantum random data.
Home-page: http://github.com/justinsloan/qdg
Author: Justin M. Sloan
Author-email: justin@justinsloan.com
Requires-Python: >=3.6
License-File: LICENSE.txt
Requires-Dist: python-dotenv
Requires-Dist: argparse
Requires-Dist: tqdm
Requires-Dist: requests
Requires-Dist: json
Requires-Dist: time
Requires-Dist: importlib
Requires-Dist: os
